{
  "versions": [
    {
      "version": "0.6.0",
      "protocols": [
        "5.0"
      ],
      "shasums_url": "https://github.com/akerl/terraform-provider-awscreds/releases/download/v0.6.0/terraform-provider-awscreds_0.6.0_SHA256SUMS",
      "shasums_signature_url": "https://github.com/akerl/terraform-provider-awscreds/releases/download/v0.6.0/terraform-provider-awscreds_0.6.0_SHA256SUMS.sig",
      "targets": [
        {
          "os": "darwin",
          "arch": "amd64",
          "filename": "terraform-provider-awscreds_0.6.0_darwin_amd64.zip",
          "download_url": "https://github.com/akerl/terraform-provider-awscreds/releases/download/v0.6.0/terraform-provider-awscreds_0.6.0_darwin_amd64.zip",
          "shasum": "73db25470c290e4c991a090cb2c8c3a18186dcfebc29bb7c2b767387d1464da9"
        },
        {
          "os": "darwin",
          "arch": "arm64",
          "filename": "terraform-provider-awscreds_0.6.0_darwin_arm64.zip",
          "download_url": "https://github.com/akerl/terraform-provider-awscreds/releases/download/v0.6.0/terraform-provider-awscreds_0.6.0_darwin_arm64.zip",
          "shasum": "b673f2e90dbb367ef73917d48e95a21461b2248873c11afc4a8fc8717631a4f7"
        },
        {
          "os": "linux",
          "arch": "amd64",
          "filename": "terraform-provider-awscreds_0.6.0_linux_amd64.zip",
          "download_url": "https://github.com/akerl/terraform-provider-awscreds/releases/download/v0.6.0/terraform-provider-awscreds_0.6.0_linux_amd64.zip",
          "shasum": "886bc2acf4550b028b522a48844ccd17e76e07ee4560e72610e663dc459df529"
        },
        {
          "os": "linux",
          "arch": "arm",
          "filename": "terraform-provider-awscreds_0.6.0_linux_arm.zip",
          "download_url": "https://github.com/akerl/terraform-provider-awscreds/releases/download/v0.6.0/terraform-provider-awscreds_0.6.0_linux_arm.zip",
          "shasum": "474dddd665209798f13296cfcf11c6a1b147bfde4f96a29eb8f608e414a337f6"
        },
        {
          "os": "linux",
          "arch": "arm64",
          "filename": "terraform-provider-awscreds_0.6.0_linux_arm64.zip",
          "download_url": "https://github.com/akerl/terraform-provider-awscreds/releases/download/v0.6.0/terraform-provider-awscreds_0.6.0_linux_arm64.zip",
          "shasum": "23d78bf3483a649fc81611897af044d66241f3b8334770131c03c17c3380ad78"
        }
      ]
    }
  ],
  "versions_errors": [
    {
      "version": "0.5.9",
      "message": "checksums not found in release",
      "utc_time": "2026-03-09T12:35:57.285605568Z"
    },
    {
      "version": "0.5.8",
      "message": "checksums not found in release",
      "utc_time": "2026-03-09T12:35:58.771313064Z"
    },
    {
      "version": "0.5.7",
      "message": "checksums not found in release",
      "utc_time": "2026-03-09T12:35:58.79522575Z"
    },
    {
      "version": "0.5.6",
      "message": "checksums not found in release",
      "utc_time": "2026-03-09T12:35:58.668668641Z"
    },
    {
      "version": "0.5.5",
      "message": "checksums not found in release",
      "utc_time": "2026-03-09T12:35:58.683200438Z"
    },
    {
      "version": "0.5.4",
      "message": "checksums not found in release",
      "utc_time": "2026-03-09T12:35:58.613347567Z"
    },
    {
      "version": "0.5.3",
      "message": "checksums not found in release",
      "utc_time": "2026-03-09T12:35:58.73151325Z"
    },
    {
      "version": "0.5.2",
      "message": "checksums not found in release",
      "utc_time": "2026-03-09T12:35:58.614434104Z"
    },
    {
      "version": "0.5.1",
      "message": "checksums not found in release",
      "utc_time": "2026-03-09T12:35:58.547794924Z"
    },
    {
      "version": "0.5.0",
      "message": "checksums not found in release",
      "utc_time": "2026-03-09T12:35:58.549113087Z"
    },
    {
      "version": "0.4.0",
      "message": "checksums not found in release",
      "utc_time": "2026-03-09T12:35:58.558970459Z"
    },
    {
      "version": "0.3.0",
      "message": "checksums not found in release",
      "utc_time": "2026-03-09T12:35:58.505674197Z"
    },
    {
      "version": "0.2.0",
      "message": "checksums not found in release",
      "utc_time": "2026-03-09T12:35:58.581207321Z"
    },
    {
      "version": "0.1.1",
      "message": "checksums not found in release",
      "utc_time": "2026-03-09T12:35:58.46525087Z"
    },
    {
      "version": "0.1.0",
      "message": "checksums not found in release",
      "utc_time": "2026-03-09T12:35:58.526373344Z"
    },
    {
      "version": "0.0.5",
      "message": "checksums not found in release",
      "utc_time": "2026-03-09T12:35:58.738768586Z"
    },
    {
      "version": "0.0.4",
      "message": "checksums not found in release",
      "utc_time": "2026-03-09T12:35:58.525804896Z"
    },
    {
      "version": "0.0.3",
      "message": "checksums not found in release",
      "utc_time": "2026-03-09T12:35:58.506425454Z"
    },
    {
      "version": "0.0.2",
      "message": "checksums not found in release",
      "utc_time": "2026-03-09T12:35:58.475228685Z"
    },
    {
      "version": "0.0.1",
      "message": "checksums not found in release",
      "utc_time": "2026-03-09T12:35:58.435975067Z"
    }
  ]
}